[
  {
    "bibl": "Matthew 21:38",
    "text": "Verebuntur forsitan filium meum: Hoc non dicitur, quia Deus ignoraret contemptum quem Iudei facturi erant Christo, sed per hoc exprimitur quid deberet fieri, ac si diceret. Verebuntur forsitanfilium meum. id est in reverentia deberent habere."
  },
  {
    "bibl": "John 11",
    "text": "Venite occidamus eum: Propter hoc tractaverunt de morte eius, ne occasione Christi venirent Romani, et auferrent eis locum et gentem, ut habetur Io. 11. et sic occiderunt eum, ut pacifice possiderent civitatem et templum : contrarium tamen accidit eis, quia per hoc in vindictam mortis Christi perdiderunt locum et gentem, quia per Titum et Vespasianum destructa est civitas et templum, et populus occisus et captivatus."
  },
  {
    "bibl": "Matthew 21:39",
    "text": "Et apprehensum eum eiecerunt extra vineam: Quia Christus extra civitatem Ierusalem crucifixus est."
  }
]