[
  {
    "bibl": "Ezekiel 16",
    "text": "Non affligam te ultra, quoniam proieci te"
  },
  {
    "bibl": "Genesis 20",
    "text": "Ego sum Deus tuus fortis, zelotes, visitans iniquitates parentum in filios usque in terciam et quartam generationem eorum, qui me oderunt."
  },
  {
    "bibl": "Isaiah 10",
    "text": "Ve Assur virga furoris mei"
  },
  {
    "bibl": "Isaiah 13",
    "text": "Erit Babilon illa gloriosa in regnis, inclita in superbiae Caldeorum, sicut subvertit Dominus Sodomam et Gomorram ; non habitabitur in sempiternum, sed requiescent ibi bestie, et replebuntur domus draconibus; habitabunt ibi strutiones, et pilosi saltabunt ibi."
  },
  {
    "bibl": "Proverbs 12",
    "text": "Non roborabitur homo ex impietate"
  },
  {
    "bibl": "Ecclesiastes 8",
    "text": "Quia non cito profertur contra iniustos sententia, absque ullo timore filii hominum perpetrant mala."
  },
  {
    "bibl": "Ecclesiasticus 5",
    "text": "Si dicas: peccavi, et quid mihi mali accidit. Altissimus est patiens redditor."
  },
  {
    "bibl": "Romans 2:4",
    "text": "An ignoras quod patientia Dei ad penitenciamh te provocat? An divicias bonitatis eius contempnis?"
  }
]